confidence/__init__.py
confidence/_version.py
confidence/confidence.py
confidence/errors.py
confidence/flag_types.py
confidence/names.py
confidence/provider/provider.py
confidence_openfeature_provider-0.2.0.dist-info/LICENSE
confidence_openfeature_provider-0.2.0.dist-info/METADATA
confidence_openfeature_provider-0.2.0.dist-info/WHEEL
confidence_openfeature_provider-0.2.0.dist-info/top_level.txt
confidence_openfeature_provider-0.2.0.dist-info/RECORD
