Metadata-Version: 2.1
Name: confidence_openfeature_provider
Version: 0.2.0
Summary: Confidence provider for the OpenFeature SDK
Author: Confidence team
License: 
Project-URL: Homepage, https://github.com/spotify/confidence-openfeature-provider-python
Classifier: Programming Language :: Python
Classifier: Programming Language :: Python :: 3
Requires-Python: >=3.8
License-File: LICENSE
Requires-Dist: requests ==2.31.0
Requires-Dist: openfeature-sdk ==0.4.2
Requires-Dist: typing-extensions ==4.9.0
Provides-Extra: dev
Requires-Dist: pytest ; extra == 'dev'
Requires-Dist: black ; extra == 'dev'
Requires-Dist: flake8 ; extra == 'dev'
Requires-Dist: requests-mock ; extra == 'dev'
